Metadata-Version: 2.0
Name: isi-sdk-8-1-1
Version: 0.2.11
Summary: Isilon SDK
Home-page: UNKNOWN
Author: UNKNOWN
Author-email: sdk@isilon.com
License: UNKNOWN
Keywords: Swagger,Isilon SDK
Platform: UNKNOWN
Requires-Dist: certifi
Requires-Dist: python-dateutil
Requires-Dist: six (>=1.10)
Requires-Dist: urllib3 (>=1.15)
